{"cameraMode":{"drawMode":0,"name":"Shaded","section":"Shading Mode"},"sceneLighting":true,"audioPlay":false,"sceneViewState":{"m_AlwaysRefresh":false,"showFog":true,"showSkybox":true,"showFlares":true,"showImageEffects":true,"showParticleSystems":true,"showVisualEffectGraphs":true,"m_FxEnabled":true},"in2DMode":false,"pivot":{"x":-0.4541435241699219,"y":0.02303527295589447,"z":1.2750020027160645},"rotation":{"x":0.29194918274879458,"y":0.5185674428939819,"z":-0.19411814212799073,"w":0.7798760533332825},"size":56.743263244628909,"orthographic":false}